{
  "id": "plot.fanren-1333-1338-tianyuancheng-auction-mqlin-scales",
  "title": "凡人修仙传 第1333-1338章：天渊城坊市拍卖会·墨麒麟真灵鳞片登场",
  "kind": "plot",
  "summary": "韩立以秘术化身虬须大汉潜入天渊城一坊市拍卖会，由炼器宗师赤大师主持；他错失真蟾灵血（被人以四百万灵石拍走），但锁定可炼葵水真灵丹的三枚墨麒麟真灵鳞片，决意势在必得，鳞片以一千五百万灵石起拍。",
  "topics": [
    "拍卖会",
    "天渊城",
    "墨麒麟鳞片",
    "葵水真灵丹",
    "法体双修",
    "灵界",
    "凡人修仙传",
    "灵界拍卖会",
    "真灵鳞片",
    "万年灵草",
    "韩立",
    "初入灵界",
    "真灵世家",
    "功法神通",
    "夺宝",
    "法器炼制"
  ],
  "keywords": [
    "天渊城",
    "坊市拍卖会",
    "赤大师",
    "墨麒麟鳞片",
    "葵水真灵丹",
    "真蟾灵血",
    "真蟾液",
    "焕心丹",
    "毒蟒令",
    "混沌万灵榜",
    "通天灵宝",
    "合体后期功法",
    "梵圣真片",
    "托天魔功",
    "明王决",
    "元磁神光",
    "噬灵天火",
    "青元剑诀",
    "飞天石屋",
    "化神",
    "炼虚",
    "Han Li",
    "auction",
    "真灵鳞片",
    "雪蛟草",
    "万年灵草",
    "平海戈",
    "韩立",
    "赤姓老者",
    "白袍老者",
    "何道友",
    "灵界",
    "拍卖",
    "三千五百万灵石",
    "阴阳化极决",
    "大周天灭绝神针",
    "五灵真君",
    "真灵世家",
    "陇家",
    "泷家",
    "叶家",
    "谷家",
    "闵家",
    "真龙血脉",
    "天凤血脉",
    "紫光灵目",
    "血痣青年",
    "玉清丹",
    "太玄殿",
    "天妙灵皇",
    "三皇",
    "第1339章",
    "True Spirit Family",
    "千宝上人",
    "万珑珠",
    "金老魔",
    "鸣老怪",
    "翡翠蛟龙",
    "金胖子",
    "吊眉汉子",
    "翁某",
    "紫枫伞",
    "五色小幡",
    "金阙玉书",
    "银蝌文",
    "大衍决",
    "分魂之术",
    "度劫分魂",
    "化身"
  ],
  "keyFacts": [
    "本拍卖会设于天渊城一坊市，凡入场者皆化神以上，亦有炼虚修士，近千化神修士齐聚——此规模唯天渊城（或三境三大主城）可见。",
    "拍卖行用『飞天石屋』隔绝神念、配遮光佩掩身，保证拍卖人隐秘。",
    "拍卖会由炼器宗师『赤大师』（赤姓白袍老者，化神中期）主动应邀主持，并亲自鉴定压轴宝物。",
    "三件压轴宝物同属一人、临时保密拍卖：①蛮荒极品材料 ②混沌万灵榜上的通天灵宝 ③一位合体期大成前辈遗留的整套主修功法。",
    "焕心丹（催进化神修为）三瓶以六十万灵石成交；毒蟒令底价两百万。",
    "真蟾灵血一罐（炼真蟾液必需材料）以四百万灵石被一懒洋洋声音的修士拍走，韩立思量后未出价放弃。",
    "压轴第一物为真灵墨麒麟脱落的三枚黑青色鳞片：可炼葵水真灵丹（化神初期服一粒可凭空进阶中期），亦为炼制水属性灵宝的最顶阶材料（有几率跻身混沌万灵榜）。",
    "墨麒麟鳞片经斧斩、三色青劫火、雷击、冰封、魔道血雾测试皆毫发无损，证为真灵鳞片。",
    "韩立因青元剑诀已修至极致、元磁神光与噬灵天火皆不助修为精进，急需高阶功法或法体双修之路（手握明王决/托天魔功/梵圣真片三套相辅相成功法）。",
    "墨麒麟鳞片三枚底价一千五百万灵石、每次加价不少于一百万，开拍即一二百万狂涨，韩立决意势在必得。",
    "韩立以三千五百万灵石拍下三枚真灵鳞片，竞价时压过一名懒洋洋声音的修士。",
    "懒洋洋声音修士曾质疑韩立无力支付、要求赤姓老者验资，随后退出竞价。",
    "韩立以多株万年灵草作抵押付款，其中一株为约一万一千年的雪蛟草，被何道友折价约七百万灵石。",
    "万年灵草是炼制所有化神级灵丹必须的药引/辅助材料，是坊市中仅次于灵石的最佳流通之物。",
    "拍卖会主持为白袍/赤姓老者，灵草鉴定由素装妇人（何道友）执行。",
    "下一件拍品为混沌万灵榜灵宝『平海戈』（蓝色短戈），底价两千万，最终亦在三千五百万被一名陌生修士拍走。",
    "「阴阳化极决」由上古五灵真君亲手创立,附带「大周天灭绝神针」神通,可临时转换自身法力的五行属性。",
    "该功法修炼条件苛刻:修炼者须为元婴期或化神期、且身具五行灵根;历代仅五灵真君一人凭此进阶到合体后期,余者多滞留化神期。",
    "拍卖底价两千万灵石,最终被与韩立争夺真灵鳞片的「懒洋洋声音」女修以四千万灵石拍走。",
    "拍走功法者经赤姓老者紫光灵目辨认确为女修,容貌奇丑系伪装,疑为叶家或谷家(天凤血脉)真灵世家子弟。",
    "血痣青年出身陇家(真龙血脉真灵世家,操控遍布三境之地的拍卖行),此次拍卖是延续上古布下的陷阱,诱出隐藏身份的真灵世家子弟。",
    "陇家为推动此局,连族藏的墨麒麟鳞片、平海戈等宝物一并拍卖,售灵石另换得五株万年灵草。",
    "赤姓老者所修紫光灵目神通一生只能施展三次,此次动用后修为受损,血痣青年许以血祭之礼助其晋阶。",
    "韩立(化神,拍得墨麒麟真灵鳞片)被赤老疑为擅育灵草的闵家之人;闵家是天妙灵皇指明的附庸真灵家族。",
    "韩立对鸡肋的阴阳化极决无兴趣,拍卖后径返洞府,欲催熟灵药炼玉清丹,并研究三枚真灵鳞片以求炼成葵水真灵丹(突破瓶颈所依)。",
    "金老魔与鸣老怪因同知『千宝上人』遗宝线索，在韩立灵地暗中较量后约定暂时联手取宝（鸣老怪不许平分）",
    "金色小人是金老魔的『度劫分魂』，翡翠小蛟是鸣老怪的化身，二者皆为炼虚修士",
    "金胖子是金老魔的小徒，吊眉汉子（翁某）是鸣老怪的徒弟",
    "金老魔随身灵宝为紫枫伞，鸣老怪以五色小幡遁走，吊眉汉子使蓝色飞刀",
    "天渊城规定：灵地主人在所属灵地上发现的宝物归主人所有",
    "韩立此时为化神修士，因修炼大衍决，神识强于化神初大成、仅逊于炼虚初期，故察觉到微弱斗法波动但仍迟一步扑空",
    "韩立闭关三日三夜炼成法器『万珑珠』：豆粒大玉珠铭刻银蝌文（仙界符文），源自参悟金阙玉书残页符箓之道",
    "万珑珠无攻防之能，须以八角银光法盘为中心、众珠互应布成超级法阵，可监控以每珠为心方圆数十里的灵气波动，激发后灵石耗费极巨"
  ],
  "entities": [
    "ent.person.x-b7ad490e",
    "ent.person.x-06125df0",
    "ent.place.x-fca77d7f",
    "ent.material.x-fbed170b",
    "ent.pill.x-4c29f4f7",
    "ent.material.x-d32a953f",
    "ent.pill.x-796c42dc",
    "ent.artifact.x-291c5889",
    "ent.technique.x-fe18e4c5",
    "ent.spell.x-076c3ca0",
    "ent.artifact.x-a6dd1779",
    "ent.technique.x-0735fc57",
    "ent.technique.x-06d6cccc",
    "ent.artifact.x-297cc575",
    "ent.beast.x-310191d0",
    "ent.item.x-17fd6fca",
    "ent.person.x-6d50f874",
    "ent.person.x-fb0a4c91",
    "ent.material.x-d46d6b07",
    "ent.material.x-05d57540",
    "ent.artifact.x-23a1294f",
    "ent.world.x-f469359c",
    "ent.person.x-9bab80b4",
    "ent.person.x-ee2a3b72",
    "ent.person.x-60952631",
    "ent.person.x-fad83c51",
    "ent.technique.x-48d3152c",
    "ent.spell.x-cbe8cdf8",
    "ent.technique.x-e43a5754",
    "ent.pill.x-93640339",
    "ent.material.x-72d05b9b",
    "ent.faction.x-870b22bf",
    "ent.faction.x-4cd2a3af",
    "ent.faction.x-c6d7e6c9",
    "ent.faction.x-2c014de5",
    "ent.race.x-0b39b0ed",
    "ent.race.x-ff2130d5",
    "ent.place.x-40ffe876",
    "ent.person.x-bc389596",
    "ent.person.x-d4b7f9e8",
    "ent.person.x-44a185f2",
    "ent.person.x-7fe6af3a",
    "ent.person.x-3d57c643",
    "ent.artifact.x-0ec75e50",
    "ent.artifact.x-2b686cef",
    "ent.artifact.x-dc157d4b",
    "ent.artifact.x-5ad02c45",
    "ent.technique.x-728616e4",
    "ent.technique.x-8e0b68c0",
    "ent.place.x-ce145ceb",
    "ent.realm.x-85759cbd",
    "ent.realm.x-636ddcea",
    "ent.realm.x-5c49f7a3"
  ],
  "fromSeq": 1333,
  "toSeq": 1338,
  "asOf": "2026-06-16",
  "timeSensitive": true,
  "validUntil": null
}
