{
  "id": "plot.fanren-2221-2226-xuanxian-mingchong-zhimu-zhansha",
  "title": "第2221-2226章 玄仙·真极之躯与螟虫之母伏诛",
  "kind": "plot",
  "summary": "韩立、宝花、蟹道人被困上古封印的海底深渊，与拥有玄仙『真极之躯』的螟虫之母强强对决；韩立点燃根源之火化巨猿、催动神念之链困敌片刻，最终由上古封印者何康老鬼降下五色天罚之雷将虫母彻底抹杀。",
  "topics": [
    "凡人修仙传",
    "灵界征战",
    "玄仙",
    "上古封印",
    "螟虫之母",
    "炼神术",
    "真仙",
    "圣界始祖之争"
  ],
  "keywords": [
    "玄仙",
    "炼仙",
    "真极之躯",
    "螟虫之母",
    "虫母",
    "韩立",
    "宝花",
    "蟹道人",
    "梵圣真魔功",
    "百脉炼宝决",
    "百造山",
    "神念之链",
    "炼神术",
    "根源之火",
    "土皇钉",
    "凤灵盘",
    "涅槃圣祖",
    "天罚之雷",
    "刑罚之雷",
    "何康",
    "巨猿",
    "玄天之宝",
    "禁术",
    "巡查使者",
    "监察仙使",
    "钵盂",
    "黑檀钵",
    "真仙",
    "瞑母",
    "金阳木",
    "紫芸之精",
    "宝符",
    "玉清灯油",
    "星空巨变",
    "界面之力",
    "元魇",
    "六极",
    "涅槃",
    "铜鸦老人",
    "翡云谷",
    "始魔之地",
    "飞升",
    "银蝌文",
    "金篆文",
    "天眼术"
  ],
  "keyFacts": [
    "玄仙是仙界异类，不修仙力真元、专炼肉身，又称『炼仙』，同阶实力远超普通仙人；『真极之躯』是玄仙的标志之一。",
    "玄仙在低阶仙人中极强，但进入仙人境中高层后修炼奇难，极少修到极高境界，故仙界中实际极罕见。",
    "螟虫之母刚修成真极之躯尚未稳固；蟹道人判断若锁住其真元、仅以肉身对抗，韩立约有三成胜机。",
    "韩立修炼梵圣真魔功，与魔族涅槃圣祖所修功法（涅槃圣体）有渊源；又得仙界百造山叛逃下界者的百脉炼宝决。",
    "韩立元婴点燃根源之火，化千余丈金甲巨猿，法力与肉身强大暴涨倍许，但后患极大、不能持久。",
    "韩立施展炼神术幻化『神念之链』（银色锁链）困住虫母片刻，自承不指望反败为胜、只为拖延。",
    "宝花以秘术度真元、化身花树女尼，催动两枚土皇钉（玄天之宝）本源之力，重伤其境界（恐跌落大乘以下）并得罪土皇钉真正主人。",
    "上古封印此虫母的两名真仙之一何康老鬼仍存活，传音相助并降下五色天罚之雷（刑罚之雷），数息间将螟虫之母飞灰湮灭。",
    "此击耗去何康仅存魂念之力九成，地宫古灯灯光转暗几近熄灭。",
    "韩立与宝花推断：现今螟虫之母体内元神疑为另一名仙界真仙占据虫母躯体；虫母身死后其力量所造虚空将塌陷。",
    "蟹道人战后真元枯竭，化迷你金蟹入韩立灵兽环休养，数月内无法再战。",
    "螟虫之母被斩杀后封印之地崩塌，韩立宝花被钵盂中真仙传送至血色祭坛（八元锁魂大阵）",
    "钵盂中男子乃当年封印螟母的两名真仙之一，仙界身份为监察仙使手下的巡查使者",
    "真仙赠宝花一根金阳木，可滋养痊愈其潜藏隐伤，随后将宝花传送离开",
    "炼神术是仙界默认的几大禁制秘术之一，能提前增幅放大神念，但修炼者多心智失常、嗜血发疯而死，被巡查使者见者必杀",
    "炼神术共七层，韩立只得前半篇、修成前两层；若万年内不到第三层，神识海将无法容纳神念之力而自爆，夺舍重修亦无幸存",
    "真仙以指点韩立修成第三层炼神术、提升两三成飞升仙界几率为报酬，求韩立用炼神术增幅的神念激发一张可无视界面之力传讯仙界的宝符",
    "当年两真仙下界铲除螟母，将成之际遇星空巨变，界面之力激增十倍以上、与仙界失联，遂自爆身躯附身两名高阶魔族建封印并元神沉睡",
    "真仙的同伴（女）曾封印其元神于黑檀钵，带玉清灯油去找被封螟母，欲借其躯修成真极之躯强行突破界面返仙界",
    "真仙另赠韩立一枚含仙界紫芸之精的玉片宝符（铭刻银蝌文、金篆文），弥补其点燃根源之火所损的本源之力",
    "韩立未即答应交易，被真仙传送离开；一年后于始魔之地边缘巨峰拦下圣界始祖元魇",
    "宝花欲夺回始祖之位，正于翡云谷对养伤的六极下手；涅槃一方多由铜鸦老人缠住",
    "元魇念宝花援救脱困之情，决定此次不干涉，并与韩立交流修炼心得"
  ],
  "entities": [
    "ent.person.x-b7ad490e",
    "ent.person.x-bee8b76d",
    "ent.beast.x-2b42f91c",
    "ent.beast.x-032b6de3",
    "ent.person.x-f7d1e4b2",
    "ent.person.x-755b31a1",
    "ent.realm.x-00ee1826",
    "ent.technique.x-eca25179",
    "ent.technique.x-1ff5f1a9",
    "ent.technique.x-2d88a969",
    "ent.spell.x-08634053",
    "ent.artifact.x-9e4500e7",
    "ent.artifact.x-458d5920",
    "ent.faction.x-a6ca0a54",
    "ent.place.x-d767b3ff",
    "ent.event.x-e7e83806",
    "ent.person.x-5dc59d7e",
    "ent.person.x-9596adff",
    "ent.person.x-60746f31",
    "ent.person.x-df64eba3",
    "ent.material.x-49b90348",
    "ent.material.x-bdb909d0",
    "ent.material.x-88c768bd",
    "ent.item.x-dc867bad",
    "ent.world.x-b944f6f5",
    "ent.place.x-a6dcc646",
    "ent.place.x-a85dafb7"
  ],
  "fromSeq": 2221,
  "toSeq": 2226,
  "asOf": "2026-06-21",
  "timeSensitive": false,
  "validUntil": null
}
