{
  "id": "ent.beast.x-656c4996",
  "type": "beast",
  "name": "鬼螂",
  "aliases": [],
  "summary": "血色螳螂状群体灵虫，最为残暴，一次能吞食整条蛟龙，凶性大发连虚灵老者都头疼。",
  "attributes": {
    "主人": "虚灵老者"
  },
  "observations": {
    "主人": [
      {
        "value": "虚灵老者",
        "docId": "plot.fanren-1855-1860-shixiandan-xuantian-canpian-shijinchong",
        "seq": 1855
      }
    ]
  },
  "firstSeq": 1855,
  "attrProvenance": {
    "主人": {
      "asOf": null,
      "docId": "plot.fanren-1855-1860-shixiandan-xuantian-canpian-shijinchong",
      "dated": false,
      "seq": 1855
    }
  },
  "contested": false,
  "contradictions": {},
  "docs": [
    "plot.fanren-1855-1860-shixiandan-xuantian-canpian-shijinchong"
  ],
  "updatedAt": "2026-06-21T07:16:44.543Z"
}
