{
  "id": "ent.person.x-5dc59d7e",
  "type": "person",
  "name": "钵盂真仙",
  "aliases": [
    "钵盂中男子",
    "黑檀钵真仙",
    "巡查使者"
  ],
  "summary": "当年封印螟虫之母的两名真仙之一，仙界监察仙使手下的巡查使者；元神被女同伴封入黑檀钵，已自破大半束缚，欲借韩立炼神术神念激发宝符向仙界求援。",
  "attributes": {
    "性别": "男",
    "身份": "巡查使者",
    "称号": "真仙",
    "存殁": "存（元神封于黑檀钵）"
  },
  "observations": {
    "性别": [
      {
        "value": "男",
        "docId": "plot.fanren-2221-2226-xuanxian-mingchong-zhimu-zhansha",
        "seq": 2221
      }
    ],
    "身份": [
      {
        "value": "巡查使者",
        "docId": "plot.fanren-2221-2226-xuanxian-mingchong-zhimu-zhansha",
        "seq": 2221
      }
    ],
    "称号": [
      {
        "value": "真仙",
        "docId": "plot.fanren-2221-2226-xuanxian-mingchong-zhimu-zhansha",
        "seq": 2221
      }
    ],
    "存殁": [
      {
        "value": "存（元神封于黑檀钵）",
        "docId": "plot.fanren-2221-2226-xuanxian-mingchong-zhimu-zhansha",
        "seq": 2221
      }
    ]
  },
  "firstSeq": 2221,
  "attrProvenance": {
    "性别": {
      "asOf": null,
      "docId": "plot.fanren-2221-2226-xuanxian-mingchong-zhimu-zhansha",
      "dated": false,
      "seq": 2221
    },
    "身份": {
      "asOf": null,
      "docId": "plot.fanren-2221-2226-xuanxian-mingchong-zhimu-zhansha",
      "dated": false,
      "seq": 2221
    },
    "称号": {
      "asOf": null,
      "docId": "plot.fanren-2221-2226-xuanxian-mingchong-zhimu-zhansha",
      "dated": false,
      "seq": 2221
    },
    "存殁": {
      "asOf": null,
      "docId": "plot.fanren-2221-2226-xuanxian-mingchong-zhimu-zhansha",
      "dated": false,
      "seq": 2221
    }
  },
  "contested": false,
  "contradictions": {},
  "docs": [
    "plot.fanren-2221-2226-xuanxian-mingchong-zhimu-zhansha"
  ],
  "updatedAt": "2026-06-21T16:05:09.815Z"
}
