{
  "id": "ent.person.x-c9457408",
  "type": "person",
  "name": "锻金之体青年",
  "aliases": [],
  "summary": "天生金属性的特殊灵体魁梧青年，被隐剑峰、火云峰争抢，最终分给幻石峰。",
  "attributes": {
    "标志特征": "锻金之体（天生金属性）"
  },
  "observations": {
    "标志特征": [
      {
        "value": "锻金之体（天生金属性）",
        "docId": "plot.fanren-594-599-luoyunzong-rumen",
        "seq": 595
      }
    ]
  },
  "firstSeq": 595,
  "attrProvenance": {
    "标志特征": {
      "asOf": null,
      "docId": "plot.fanren-594-599-luoyunzong-rumen",
      "dated": false,
      "seq": 595
    }
  },
  "contested": false,
  "contradictions": {},
  "docs": [
    "plot.fanren-594-599-luoyunzong-rumen"
  ],
  "updatedAt": "2026-06-14T19:32:47.671Z"
}
