{
  "id": "ent.person.x-572a40da",
  "type": "person",
  "name": "黑脸道士",
  "aliases": [],
  "summary": "身处遥远界面的道士，持真魂之牌；察觉师兄弟（仙界使者）真魂出事，决意寻找。",
  "attributes": {
    "外貌": "黑脸道士"
  },
  "observations": {
    "外貌": [
      {
        "value": "黑脸道士",
        "docId": "plot.fanren-2005-2010-bazu-moxi-xianhundan",
        "seq": 2005
      }
    ]
  },
  "firstSeq": 2005,
  "attrProvenance": {
    "外貌": {
      "asOf": null,
      "docId": "plot.fanren-2005-2010-bazu-moxi-xianhundan",
      "dated": false,
      "seq": 2005
    }
  },
  "contested": false,
  "contradictions": {},
  "docs": [
    "plot.fanren-2005-2010-bazu-moxi-xianhundan"
  ],
  "updatedAt": "2026-06-21T11:17:22.719Z"
}
