{
  "id": "ent.person.x-2c3a5150",
  "type": "person",
  "name": "柳儿",
  "aliases": [
    "蓝衫少女",
    "柳儿姑娘"
  ],
  "summary": "天东商号车厢中年纪最长、话最少的蓝衫少女。",
  "attributes": {
    "性别": "女",
    "外貌": "蓝衫，车中年纪最长、蓝衫",
    "阵营": "天东商号",
    "身份": "天东商号少女/管事"
  },
  "observations": {
    "性别": [
      {
        "value": "女",
        "docId": "plot.fanren-1261-1266-blood-curse-tiandong",
        "seq": 1261
      }
    ],
    "外貌": [
      {
        "value": "蓝衫，车中年纪最长",
        "docId": "plot.fanren-1261-1266-blood-curse-tiandong",
        "seq": 1261
      },
      {
        "value": "蓝衫",
        "docId": "plot.fanren-1261-1266-blood-curse-tiandong",
        "seq": 1261
      }
    ],
    "阵营": [
      {
        "value": "天东商号",
        "docId": "plot.fanren-1261-1266-blood-curse-tiandong",
        "seq": 1261
      }
    ],
    "身份": [
      {
        "value": "天东商号少女/管事",
        "docId": "plot.fanren-1261-1266-blood-curse-tiandong",
        "seq": 1261
      }
    ]
  },
  "firstSeq": 1261,
  "attrProvenance": {
    "性别": {
      "asOf": null,
      "docId": "plot.fanren-1261-1266-blood-curse-tiandong",
      "dated": false,
      "seq": 1261
    },
    "外貌": {
      "asOf": null,
      "docId": "plot.fanren-1261-1266-blood-curse-tiandong",
      "dated": false,
      "seq": 1261
    },
    "阵营": {
      "asOf": null,
      "docId": "plot.fanren-1261-1266-blood-curse-tiandong",
      "dated": false,
      "seq": 1261
    },
    "身份": {
      "asOf": null,
      "docId": "plot.fanren-1261-1266-blood-curse-tiandong",
      "dated": false,
      "seq": 1261
    }
  },
  "contested": false,
  "contradictions": {},
  "docs": [
    "plot.fanren-1261-1266-blood-curse-tiandong"
  ],
  "updatedAt": "2026-06-16T10:03:55.741Z"
}
