{
  "id": "ent.person.x-151e2059",
  "type": "person",
  "name": "银发老者(谷兄)",
  "aliases": [],
  "summary": "天渊城合体存在，韩立战友，被匈姓古魔大汉撕下一臂；持七焰扇、同心环。",
  "attributes": {
    "小阶段": "合体期",
    "阵营": "人族",
    "外貌": "银发、衣襟尽碎、缺一臂",
    "标志特征": "祭七焰扇与同心环"
  },
  "observations": {
    "小阶段": [
      {
        "value": "合体期",
        "docId": "plot.tianyuan-great-war-1981-1986",
        "seq": 1981
      }
    ],
    "阵营": [
      {
        "value": "人族",
        "docId": "plot.tianyuan-great-war-1981-1986",
        "seq": 1981
      }
    ],
    "外貌": [
      {
        "value": "银发、衣襟尽碎、缺一臂",
        "docId": "plot.tianyuan-great-war-1981-1986",
        "seq": 1981
      }
    ],
    "标志特征": [
      {
        "value": "祭七焰扇与同心环",
        "docId": "plot.tianyuan-great-war-1981-1986",
        "seq": 1981
      }
    ]
  },
  "firstSeq": 1981,
  "attrProvenance": {
    "小阶段": {
      "asOf": null,
      "docId": "plot.tianyuan-great-war-1981-1986",
      "dated": false,
      "seq": 1981
    },
    "阵营": {
      "asOf": null,
      "docId": "plot.tianyuan-great-war-1981-1986",
      "dated": false,
      "seq": 1981
    },
    "外貌": {
      "asOf": null,
      "docId": "plot.tianyuan-great-war-1981-1986",
      "dated": false,
      "seq": 1981
    },
    "标志特征": {
      "asOf": null,
      "docId": "plot.tianyuan-great-war-1981-1986",
      "dated": false,
      "seq": 1981
    }
  },
  "contested": false,
  "contradictions": {},
  "docs": [
    "plot.tianyuan-great-war-1981-1986"
  ],
  "updatedAt": "2026-06-21T10:38:29.930Z"
}
