{
  "id": "ent.person.x-618e8ada",
  "type": "person",
  "name": "柳玉",
  "aliases": [
    "柳姓女修",
    "柳姐姐",
    "柳玉师姐",
    "柳玉此女",
    "白衣大美女",
    "柳姓修士",
    "柳玉道友"
  ],
  "summary": "御灵宗女修士，木属性灵根，至木灵婴最佳合体者之一，被派往元武国查找灵婴。",
  "attributes": {
    "性别": "女",
    "身份": "御灵宗弟子、御灵宗弟子、融合灵婴候选者、韩立弟子、韩立记名弟子、落云宗弟子、落云宗元婴长老以下第一人、落云宗修士、天道盟修士、御灵宗融合灵婴候选者、记名弟子、白凤峰副峰主、韩立正式弟子、落云宗长老、落云宗修士/吕洛助手",
    "标志特征": "身上携有六翼霜蚣幼虫",
    "阵营": "落云宗",
    "外貌": "高挑白衣美女、白衣、容貌娇柔、肤如吹弹可破、白袍女修、高挑白衣美貌、白衣、容貌娇柔、白袍貌美女修",
    "存殁": "下落不明",
    "种族": "人",
    "小阶段": "结丹",
    "出身地": "魔道"
  },
  "observations": {
    "性别": [
      {
        "value": "女",
        "docId": "plot.fanren-ch648-zhimu-lingying",
        "seq": 649
      }
    ],
    "身份": [
      {
        "value": "御灵宗弟子",
        "docId": "plot.fanren-ch648-zhimu-lingying",
        "seq": 649
      },
      {
        "value": "御灵宗弟子、融合灵婴候选者",
        "docId": "plot.fanren-ch666-liuyu",
        "seq": 667
      },
      {
        "value": "韩立弟子",
        "docId": "plot.fanren-781-786-nangong-jingbian-jianzhen-chucheng",
        "seq": 781
      },
      {
        "value": "韩立记名弟子",
        "docId": "plot.fanren-1167-1172-return-luoyunzong",
        "seq": 1165
      },
      {
        "value": "落云宗弟子",
        "docId": "plot.fanren-1183-1188-fuzhong-tonghua-dujie",
        "seq": 1183,
        "note": "由记名弟子转正式弟子"
      },
      {
        "value": "落云宗元婴长老以下第一人",
        "docId": "lore.fanren-1215-linggen-wuxing-heyi",
        "seq": 1213
      },
      {
        "value": "落云宗修士",
        "docId": "plot.fanren-1219-1224-author-note-vote-request",
        "seq": 1219
      },
      {
        "value": "天道盟修士",
        "docId": "plot.fanren-661-666-noxious-gold-sword-trail-exposed",
        "seq": 661
      },
      {
        "value": "御灵宗融合灵婴候选者",
        "docId": "plot.fanren-666-liuyu",
        "seq": 667
      },
      {
        "value": "记名弟子",
        "docId": "plot.fanren-666-liuyu",
        "seq": 667
      },
      {
        "value": "白凤峰副峰主",
        "docId": "plot.fanren-666-liuyu",
        "seq": 667
      },
      {
        "value": "韩立正式弟子",
        "docId": "plot.fanren-1183-1188-fuzhong-tonghua-dujie",
        "seq": 1183,
        "note": "本片段由记名弟子转正"
      },
      {
        "value": "落云宗长老",
        "docId": "plot.fanren-ch1213-1218-wuxing-heyi-poyang-yuanci-shan",
        "seq": 1213
      },
      {
        "value": "落云宗修士/吕洛助手",
        "docId": "plot.fanren-1219-1224-zaidu-yuanyou-tianjidian",
        "seq": 1219
      }
    ],
    "标志特征": [
      {
        "value": "木属性灵根",
        "docId": "plot.fanren-ch648-zhimu-lingying",
        "seq": 649
      },
      {
        "value": "木灵根",
        "docId": "plot.fanren-666-liuyu",
        "seq": 667
      },
      {
        "value": "身上携有六翼霜蚣幼虫",
        "docId": "plot.ch1179-inner-valley-seek-three-women",
        "seq": 1177
      }
    ],
    "阵营": [
      {
        "value": "魔道",
        "docId": "plot.fanren-ch660-shijin-lingjian",
        "seq": 661
      },
      {
        "value": "落云宗",
        "docId": "plot.fanren-1173-second-yuanying-tiansha-moshi",
        "seq": 1171
      }
    ],
    "外貌": [
      {
        "value": "高挑白衣美女",
        "docId": "plot.fanren-ch660-shijin-lingjian",
        "seq": 661
      },
      {
        "value": "白衣、容貌娇柔、肤如吹弹可破",
        "docId": "plot.fanren-ch666-liuyu",
        "seq": 667
      },
      {
        "value": "白袍女修",
        "docId": "plot.fanren-1177-1182-xueyue-miling-rescue-three-women",
        "seq": 1177
      },
      {
        "value": "高挑白衣美貌",
        "docId": "plot.fanren-661-666-noxious-gold-sword-trail-exposed",
        "seq": 661
      },
      {
        "value": "白衣、容貌娇柔",
        "docId": "plot.fanren-666-liuyu",
        "seq": 667
      },
      {
        "value": "白袍貌美女修",
        "docId": "plot.fanren-1184-shou-ying-capture-second-nascent-soul",
        "seq": 1177
      }
    ],
    "存殁": [
      {
        "value": "活（被擒）",
        "docId": "plot.fanren-ch660-shijin-lingjian",
        "seq": 661
      },
      {
        "value": "失踪",
        "docId": "plot.fanren-1173-second-yuanying-tiansha-moshi",
        "seq": 1171,
        "note": "疑困坠魔谷内谷"
      },
      {
        "value": "下落不明",
        "docId": "plot.ch1179-inner-valley-seek-three-women",
        "seq": 1177,
        "note": "被掳走，韩立正在追踪"
      }
    ],
    "种族": [
      {
        "value": "人",
        "docId": "plot.fanren-ch666-liuyu",
        "seq": 667
      },
      {
        "value": "人族",
        "docId": "plot.fanren-ch648-zhimu-lingying",
        "seq": 649
      }
    ],
    "小阶段": [
      {
        "value": "结丹期",
        "docId": "plot.fanren-ch666-liuyu",
        "seq": 667
      },
      {
        "value": "结丹",
        "docId": "plot.fanren-1173-second-yuanying-tiansha-moshi",
        "seq": 1171
      }
    ],
    "出身地": [
      {
        "value": "魔道",
        "docId": "plot.fanren-1167-1172-return-luoyunzong",
        "seq": 1165
      },
      {
        "value": "柳家",
        "docId": "plot.fanren-666-liuyu",
        "seq": 667
      }
    ]
  },
  "firstSeq": 649,
  "attrProvenance": {
    "性别": {
      "asOf": null,
      "docId": "plot.fanren-ch648-zhimu-lingying",
      "dated": false,
      "seq": 649
    },
    "身份": {
      "asOf": null,
      "docId": "plot.fanren-ch648-zhimu-lingying",
      "dated": false,
      "seq": 649
    },
    "标志特征": {
      "asOf": null,
      "docId": "plot.ch1179-inner-valley-seek-three-women",
      "dated": false,
      "seq": 1177
    },
    "阵营": {
      "asOf": null,
      "docId": "plot.fanren-1173-second-yuanying-tiansha-moshi",
      "dated": false,
      "seq": 1171
    },
    "外貌": {
      "asOf": null,
      "docId": "plot.fanren-ch660-shijin-lingjian",
      "dated": false,
      "seq": 661
    },
    "存殁": {
      "asOf": null,
      "docId": "plot.ch1179-inner-valley-seek-three-women",
      "dated": false,
      "seq": 1177,
      "note": "被掳走，韩立正在追踪"
    },
    "种族": {
      "asOf": null,
      "docId": "plot.fanren-ch666-liuyu",
      "dated": false,
      "seq": 667
    },
    "小阶段": {
      "asOf": null,
      "docId": "plot.fanren-1173-second-yuanying-tiansha-moshi",
      "dated": false,
      "seq": 1171
    },
    "出身地": {
      "asOf": null,
      "docId": "plot.fanren-1167-1172-return-luoyunzong",
      "dated": false,
      "seq": 1165
    }
  },
  "contested": false,
  "contradictions": {},
  "docs": [
    "plot.fanren-ch648-zhimu-lingying",
    "plot.fanren-ch660-shijin-lingjian",
    "plot.fanren-ch666-liuyu",
    "plot.fanren-781-786-nangong-jingbian-jianzhen-chucheng",
    "plot.fanren-1167-1172-return-luoyunzong",
    "plot.fanren-1173-second-yuanying-tiansha-moshi",
    "plot.fanren-1177-1182-xueyue-miling-rescue-three-women",
    "plot.fanren-1183-1188-fuzhong-tonghua-dujie",
    "plot.fanren-1196-er-nv",
    "lore.fanren-1215-linggen-wuxing-heyi",
    "plot.fanren-1219-1224-author-note-vote-request",
    "plot.fanren-1249-1254-han-li-advances-to-huashen",
    "plot.fanren-661-666-noxious-gold-sword-trail-exposed",
    "plot.fanren-666-liuyu",
    "plot.fanren-781-nangong-jingbian",
    "plot.fanren-ch1167-1172-return-to-luoyun-sect",
    "plot.fanren-1173-second-yuanying-tiansha-corpse",
    "plot.ch1179-inner-valley-seek-three-women",
    "plot.ch1180-rescue-lava-lake-mupeilin",
    "plot.fanren-1181-chonglin-qiling",
    "plot.fanren-1184-shou-ying-capture-second-nascent-soul",
    "plot.fanren-ch1213-1218-wuxing-heyi-poyang-yuanci-shan",
    "plot.fanren-1219-1224-zaidu-yuanyou-tianjidian",
    "plot.fanren-1251-li-ya-er-yao"
  ],
  "updatedAt": "2026-06-20T06:47:36.381Z"
}
