{
  "id": "ent.person.x-653609cb",
  "type": "person",
  "name": "邪莲圣祖",
  "aliases": [
    "邪莲",
    "邪莲道友",
    "绿色宫装女子"
  ],
  "summary": "万花山脉朝天峰的圣祖级大乘，宝花之同胞妹妹，神情阴冷；向韩立等揭示始印之地真相。",
  "attributes": {
    "小阶段": "大乘期",
    "称号": "圣祖",
    "性别": "女",
    "外貌": "绿色宫装、面容酷似宝花、神情阴冷",
    "阵营": "魔界",
    "标志特征": "面容酷似宝花"
  },
  "observations": {
    "小阶段": [
      {
        "value": "大乘期",
        "docId": "plot.fanren-2210-2215-mingchong-xieliansheng",
        "seq": 2191
      }
    ],
    "称号": [
      {
        "value": "圣祖",
        "docId": "plot.fanren-2210-2215-mingchong-xieliansheng",
        "seq": 2191
      }
    ],
    "性别": [
      {
        "value": "女",
        "docId": "plot.fanren-2210-2215-mingchong-xieliansheng",
        "seq": 2191
      }
    ],
    "外貌": [
      {
        "value": "绿色宫装、面容酷似宝花、神情阴冷",
        "docId": "plot.fanren-2210-2215-mingchong-xieliansheng",
        "seq": 2191
      }
    ],
    "阵营": [
      {
        "value": "魔界",
        "docId": "plot.fanren-2197-2202-shengjie-juhui-tongya-laoren",
        "seq": 2197
      }
    ],
    "标志特征": [
      {
        "value": "面容酷似宝花",
        "docId": "plot.fanren-2197-2202-shengjie-juhui-tongya-laoren",
        "seq": 2197
      }
    ]
  },
  "firstSeq": 2191,
  "attrProvenance": {
    "小阶段": {
      "asOf": null,
      "docId": "plot.fanren-2210-2215-mingchong-xieliansheng",
      "dated": false,
      "seq": 2191
    },
    "称号": {
      "asOf": null,
      "docId": "plot.fanren-2210-2215-mingchong-xieliansheng",
      "dated": false,
      "seq": 2191
    },
    "性别": {
      "asOf": null,
      "docId": "plot.fanren-2210-2215-mingchong-xieliansheng",
      "dated": false,
      "seq": 2191
    },
    "外貌": {
      "asOf": null,
      "docId": "plot.fanren-2210-2215-mingchong-xieliansheng",
      "dated": false,
      "seq": 2191
    },
    "阵营": {
      "asOf": null,
      "docId": "plot.fanren-2197-2202-shengjie-juhui-tongya-laoren",
      "dated": false,
      "seq": 2197
    },
    "标志特征": {
      "asOf": null,
      "docId": "plot.fanren-2197-2202-shengjie-juhui-tongya-laoren",
      "dated": false,
      "seq": 2197
    }
  },
  "contested": false,
  "contradictions": {},
  "docs": [
    "plot.fanren-2210-2215-mingchong-xieliansheng",
    "plot.fanren-2197-2202-shengjie-juhui-tongya-laoren"
  ],
  "updatedAt": "2026-06-21T15:43:42.255Z"
}
