{
  "id": "ent.person.x-d8a63dc8",
  "type": "person",
  "name": "云露老魔",
  "aliases": [
    "古老魔",
    "云露真人",
    "古姓老怪物",
    "云露道友",
    "云露老怪",
    "阴柔青年",
    "面容阴柔青年",
    "云露"
  ],
  "summary": "合欢宗元婴中期老魔，天生阴阳同体，修最顶尖采补魔功，恶名遍天南。",
  "attributes": {
    "种族": "飞灵族",
    "小阶段": "元婴中期、元婴、炼虚初期",
    "道号": "云露真人",
    "标志特征": "阴阳同体、阴柔脂粉气、周身脂粉之气、背生双翅、驱银色电弧、阴阳同体、身带阴柔脂粉气",
    "称号": "云露老魔、云露真人",
    "阵营": "魔道·合欢宗、魔道、合欢宗",
    "外貌": "面容阴柔",
    "身份": "老魔",
    "出身地": "天鹏族",
    "性别": "男",
    "性格": "不甘示弱"
  },
  "observations": {
    "种族": [
      {
        "value": "人",
        "docId": "plot.fanren-751-756-huayan-leizhu-yunlu-laomo",
        "seq": 751
      },
      {
        "value": "天鹏族",
        "docId": "plot.fanren-1417-1422-kunpeng-sheli-jingzhe-shier-bian",
        "seq": 1417
      },
      {
        "value": "飞灵族",
        "docId": "plot.fanren-1423-1428-jiangshou-yinleizhu-jidan",
        "seq": 1423
      }
    ],
    "小阶段": [
      {
        "value": "元婴中期",
        "docId": "plot.fanren-751-756-huayan-leizhu-yunlu-laomo",
        "seq": 751
      },
      {
        "value": "元婴",
        "docId": "plot.fanren-751-756-huayan-leizhu-yunlu-laomo",
        "seq": 751
      },
      {
        "value": "炼虚初期",
        "docId": "plot.fanren-1417-1422-kunpeng-sheli-jingzhe-shier-bian",
        "seq": 1417
      }
    ],
    "道号": [
      {
        "value": "云露真人",
        "docId": "plot.fanren-751-756-huayan-leizhu-yunlu-laomo",
        "seq": 751
      }
    ],
    "标志特征": [
      {
        "value": "阴阳同体、阴柔脂粉气",
        "docId": "plot.fanren-751-756-huayan-leizhu-yunlu-laomo",
        "seq": 751
      },
      {
        "value": "周身脂粉之气",
        "docId": "plot.fanren-751-756-huayan-leizhu-yunlu-laomo",
        "seq": 751
      },
      {
        "value": "背生双翅、驱银色电弧",
        "docId": "plot.fanren-1423-1428-jiangshou-yinleizhu-jidan",
        "seq": 1423
      },
      {
        "value": "阴阳同体、身带阴柔脂粉气",
        "docId": "plot.fanren-751-756-huayan-leizhu-yunlu-laomo",
        "seq": 751
      }
    ],
    "称号": [
      {
        "value": "云露老魔",
        "docId": "plot.fanren-751-756-huayan-leizhu-yunlu-laomo",
        "seq": 751
      },
      {
        "value": "云露真人",
        "docId": "plot.fanren-751-756-huayan-leizhu-yunlu-laomo",
        "seq": 751
      }
    ],
    "阵营": [
      {
        "value": "魔道·合欢宗",
        "docId": "plot.fanren-751-756-huayan-leizhu-yunlu-laomo",
        "seq": 751
      },
      {
        "value": "魔道",
        "docId": "plot.fanren-751-756-huayan-leizhu-yunlu-laomo",
        "seq": 751
      },
      {
        "value": "合欢宗",
        "docId": "plot.fanren-775-780-border-war-end-yuanming-lamp",
        "seq": 775
      }
    ],
    "外貌": [
      {
        "value": "俊美年轻锦袍男子(实为老怪)",
        "docId": "plot.fanren-751-756-huayan-leizhu-yunlu-laomo",
        "seq": 751
      },
      {
        "value": "相貌俊美的阴柔青年",
        "docId": "plot.fanren-775-780-border-war-end-yuanming-lamp",
        "seq": 775
      },
      {
        "value": "面容阴柔",
        "docId": "plot.fanren-1417-1422-kunpeng-sheli-jingzhe-shier-bian",
        "seq": 1417
      }
    ],
    "身份": [
      {
        "value": "老魔",
        "docId": "plot.fanren-1196-er-nv",
        "seq": 1195
      },
      {
        "value": "合欢宗修士",
        "docId": "plot.fanren-751-756-huayan-leizhu-yunlu-laomo",
        "seq": 751
      }
    ],
    "出身地": [
      {
        "value": "天鹏族",
        "docId": "plot.fanren-1417-1422-kunpeng-sheli-jingzhe-shier-bian",
        "seq": 1417
      }
    ],
    "性别": [
      {
        "value": "男",
        "docId": "plot.fanren-1423-1428-jiangshou-yinleizhu-jidan",
        "seq": 751,
        "note": "阴阳同体，显二十余岁锦袍美男身"
      }
    ],
    "性格": [
      {
        "value": "不甘示弱",
        "docId": "plot.fanren-1423-1428-jiangshou-yinleizhu-jidan",
        "seq": 1423
      },
      {
        "value": "好色、采补",
        "docId": "plot.fanren-751-756-huayan-leizhu-yunlu-laomo",
        "seq": 751
      }
    ]
  },
  "firstSeq": 751,
  "attrProvenance": {
    "种族": {
      "asOf": null,
      "docId": "plot.fanren-1423-1428-jiangshou-yinleizhu-jidan",
      "dated": false,
      "seq": 1423
    },
    "小阶段": {
      "asOf": null,
      "docId": "plot.fanren-751-756-huayan-leizhu-yunlu-laomo",
      "dated": false,
      "seq": 751
    },
    "道号": {
      "asOf": null,
      "docId": "plot.fanren-751-756-huayan-leizhu-yunlu-laomo",
      "dated": false,
      "seq": 751
    },
    "标志特征": {
      "asOf": null,
      "docId": "plot.fanren-751-756-huayan-leizhu-yunlu-laomo",
      "dated": false,
      "seq": 751
    },
    "称号": {
      "asOf": null,
      "docId": "plot.fanren-751-756-huayan-leizhu-yunlu-laomo",
      "dated": false,
      "seq": 751
    },
    "阵营": {
      "asOf": null,
      "docId": "plot.fanren-751-756-huayan-leizhu-yunlu-laomo",
      "dated": false,
      "seq": 751
    },
    "外貌": {
      "asOf": null,
      "docId": "plot.fanren-1417-1422-kunpeng-sheli-jingzhe-shier-bian",
      "dated": false,
      "seq": 1417
    },
    "身份": {
      "asOf": null,
      "docId": "plot.fanren-1196-er-nv",
      "dated": false,
      "seq": 1195
    },
    "出身地": {
      "asOf": null,
      "docId": "plot.fanren-1417-1422-kunpeng-sheli-jingzhe-shier-bian",
      "dated": false,
      "seq": 1417
    },
    "性别": {
      "asOf": null,
      "docId": "plot.fanren-1423-1428-jiangshou-yinleizhu-jidan",
      "dated": false,
      "seq": 751,
      "note": "阴阳同体，显二十余岁锦袍美男身"
    },
    "性格": {
      "asOf": null,
      "docId": "plot.fanren-1423-1428-jiangshou-yinleizhu-jidan",
      "dated": false,
      "seq": 1423
    }
  },
  "contested": false,
  "contradictions": {},
  "docs": [
    "plot.fanren-751-756-huayan-leizhu-yunlu-laomo",
    "plot.fanren-757-762-gengjing-jiangling-fu",
    "plot.fanren-775-780-border-war-end-yuanming-lamp",
    "plot.fanren-1196-er-nv",
    "plot.fanren-1417-1422-kunpeng-sheli-jingzhe-shier-bian",
    "plot.fanren-1423-1428-jiangshou-yinleizhu-jidan",
    "plot.fanren-757-bingxuecan-yu-gengjing"
  ],
  "updatedAt": "2026-06-17T12:10:50.229Z"
}
