{
  "id": "ent.person.x-be68283e",
  "type": "person",
  "name": "红云大长老",
  "aliases": [
    "红云长老",
    "红云",
    "第九代大长老"
  ],
  "summary": "天鹏族第九代大长老，独创惊蛰决，因真血反噬发疯坐化，舍利残留惊蛰决口诀与凶暴神念。",
  "attributes": {
    "种族": "飞灵族、天鹏族",
    "身份": "天鹏族第九代大长老",
    "存殁": "死亡",
    "死因": "创惊蛰决遭诸多真血反噬，发疯而亡、诸真血反噬、发疯坐化",
    "性别": "男",
    "小阶段": "合体后期",
    "称号": "第九代大长老",
    "结局": "舍利被韩立炼化，惊蛰决落入韩立之手"
  },
  "observations": {
    "种族": [
      {
        "value": "飞灵族",
        "docId": "plot.fanren-1417-1422-kunpeng-sheli-jingzhe-shier-bian",
        "seq": 1417
      },
      {
        "value": "天鹏族",
        "docId": "plot.fmxxz-ch1417-1422-kunpeng-sheli-jingzhe-shi-er-bian",
        "seq": 1417
      }
    ],
    "身份": [
      {
        "value": "天鹏族第九代大长老",
        "docId": "plot.fanren-1417-1422-kunpeng-sheli-jingzhe-shier-bian",
        "seq": 1417
      }
    ],
    "存殁": [
      {
        "value": "死亡",
        "docId": "plot.fanren-1417-1422-kunpeng-sheli-jingzhe-shier-bian",
        "seq": 1417
      }
    ],
    "死因": [
      {
        "value": "创惊蛰决遭诸多真血反噬，发疯而亡",
        "docId": "plot.fanren-1417-1422-kunpeng-sheli-jingzhe-shier-bian",
        "seq": 1417
      },
      {
        "value": "诸真血反噬、发疯坐化",
        "docId": "plot.fmxxz-ch1417-1422-kunpeng-sheli-jingzhe-shi-er-bian",
        "seq": 1417
      }
    ],
    "性别": [
      {
        "value": "男",
        "docId": "plot.fmxxz-ch1417-1422-kunpeng-sheli-jingzhe-shi-er-bian",
        "seq": 1417
      }
    ],
    "小阶段": [
      {
        "value": "合体后期",
        "docId": "plot.fmxxz-ch1417-1422-kunpeng-sheli-jingzhe-shi-er-bian",
        "seq": 1417
      }
    ],
    "称号": [
      {
        "value": "第九代大长老",
        "docId": "plot.fmxxz-ch1417-1422-kunpeng-sheli-jingzhe-shi-er-bian",
        "seq": 1417
      }
    ],
    "结局": [
      {
        "value": "舍利被韩立炼化，惊蛰决落入韩立之手",
        "docId": "plot.fmxxz-ch1417-1422-kunpeng-sheli-jingzhe-shi-er-bian",
        "seq": 1417
      }
    ]
  },
  "firstSeq": 1417,
  "attrProvenance": {
    "种族": {
      "asOf": null,
      "docId": "plot.fanren-1417-1422-kunpeng-sheli-jingzhe-shier-bian",
      "dated": false,
      "seq": 1417
    },
    "身份": {
      "asOf": null,
      "docId": "plot.fanren-1417-1422-kunpeng-sheli-jingzhe-shier-bian",
      "dated": false,
      "seq": 1417
    },
    "存殁": {
      "asOf": null,
      "docId": "plot.fanren-1417-1422-kunpeng-sheli-jingzhe-shier-bian",
      "dated": false,
      "seq": 1417
    },
    "死因": {
      "asOf": null,
      "docId": "plot.fanren-1417-1422-kunpeng-sheli-jingzhe-shier-bian",
      "dated": false,
      "seq": 1417
    },
    "性别": {
      "asOf": null,
      "docId": "plot.fmxxz-ch1417-1422-kunpeng-sheli-jingzhe-shi-er-bian",
      "dated": false,
      "seq": 1417
    },
    "小阶段": {
      "asOf": null,
      "docId": "plot.fmxxz-ch1417-1422-kunpeng-sheli-jingzhe-shi-er-bian",
      "dated": false,
      "seq": 1417
    },
    "称号": {
      "asOf": null,
      "docId": "plot.fmxxz-ch1417-1422-kunpeng-sheli-jingzhe-shi-er-bian",
      "dated": false,
      "seq": 1417
    },
    "结局": {
      "asOf": null,
      "docId": "plot.fmxxz-ch1417-1422-kunpeng-sheli-jingzhe-shi-er-bian",
      "dated": false,
      "seq": 1417
    }
  },
  "contested": false,
  "contradictions": {},
  "docs": [
    "plot.fanren-1417-1422-kunpeng-sheli-jingzhe-shier-bian",
    "plot.fmxxz-ch1417-1422-kunpeng-sheli-jingzhe-shi-er-bian"
  ],
  "updatedAt": "2026-06-20T11:25:39.498Z"
}
