{
  "id": "ent.place.x-37c0772f",
  "type": "place",
  "name": "玄天峰",
  "aliases": [],
  "summary": "黑袍人首封玉简中所指的约见之地（后改约天柱山峰顶）。",
  "attributes": {
    "类型": "山峰"
  },
  "observations": {
    "类型": [
      {
        "value": "山峰",
        "docId": "plot.fanren-781-786-nangong-jingbian-jianzhen-chucheng",
        "seq": 781
      }
    ]
  },
  "firstSeq": 781,
  "attrProvenance": {
    "类型": {
      "asOf": null,
      "docId": "plot.fanren-781-786-nangong-jingbian-jianzhen-chucheng",
      "dated": false,
      "seq": 781
    }
  },
  "contested": false,
  "contradictions": {},
  "docs": [
    "plot.fanren-781-786-nangong-jingbian-jianzhen-chucheng"
  ],
  "updatedAt": "2026-06-15T03:58:16.672Z"
}
