{
  "id": "ent.faction.x-573996d0",
  "type": "faction",
  "name": "封河涧萧家",
  "aliases": [
    "萧家"
  ],
  "summary": "允州封河涧的一个小修仙家族，无名，安排族人萧振在世俗界负责财源。",
  "attributes": {
    "等级": "小修仙家族",
    "据点": "允州封河涧"
  },
  "observations": {
    "等级": [
      {
        "value": "小修仙家族",
        "docId": "plot.fanren-vol3-c289-294-xiaowangye-xiaojia",
        "seq": 289
      }
    ],
    "据点": [
      {
        "value": "允州封河涧",
        "docId": "plot.fanren-vol3-c289-294-xiaowangye-xiaojia",
        "seq": 289
      }
    ]
  },
  "firstSeq": 289,
  "attrProvenance": {
    "等级": {
      "asOf": null,
      "docId": "plot.fanren-vol3-c289-294-xiaowangye-xiaojia",
      "dated": false,
      "seq": 289
    },
    "据点": {
      "asOf": null,
      "docId": "plot.fanren-vol3-c289-294-xiaowangye-xiaojia",
      "dated": false,
      "seq": 289
    }
  },
  "contested": false,
  "contradictions": {},
  "docs": [
    "plot.fanren-vol3-c289-294-xiaowangye-xiaojia"
  ],
  "updatedAt": "2026-06-14T09:14:36.144Z"
}
