{
  "id": "ent.pill.x-7eded06e",
  "type": "pill",
  "name": "清虚丹",
  "aliases": [],
  "summary": "可保灵物神智不被暴血咒夺去的丹药，银翅夜叉曾暗分一粒予圭姓丑妇。",
  "attributes": {
    "功效": "保持神智、抵御暴血咒"
  },
  "observations": {
    "功效": [
      {
        "value": "保持神智、抵御暴血咒",
        "docId": "plot.fanren-1003-qunmo-yinxian",
        "seq": 1003
      }
    ]
  },
  "firstSeq": 1003,
  "attrProvenance": {
    "功效": {
      "asOf": null,
      "docId": "plot.fanren-1003-qunmo-yinxian",
      "dated": false,
      "seq": 1003
    }
  },
  "contested": false,
  "contradictions": {},
  "docs": [
    "plot.fanren-1003-qunmo-yinxian"
  ],
  "updatedAt": "2026-06-16T03:59:21.446Z"
}
