{
  "id": "ent.material.x-a5c63eeb",
  "type": "material",
  "name": "冥焰果",
  "aliases": [
    "冥焰树果实"
  ],
  "summary": "本次试炼目标灵果，生于黑暗与秽气最凝重之地，约五百年成熟一次、每株仅生一枚；地渊一层无，二层或有少量，三层必有。",
  "attributes": {
    "类型": "灵药/灵果",
    "用途": "试炼目标",
    "稀有度": "罕见",
    "产地": "地渊（秽气最浓处，三层必有）、地渊深层、地渊二层、冰煞之地、地渊腐叶林深处水潭边、地渊"
  },
  "observations": {
    "类型": [
      {
        "value": "灵果/灵物",
        "docId": "plot.fanren-1429-1434-zhuyinzi-jiaojichang-shitan",
        "seq": 1429
      },
      {
        "value": "灵果",
        "docId": "plot.fanren-1438-yin-zhu-feng",
        "seq": 1435
      },
      {
        "value": "灵药/灵果",
        "docId": "plot.fanren-1447-1452-blood-puppets-and-pet-advance",
        "seq": 1447
      }
    ],
    "用途": [
      {
        "value": "试炼凭证",
        "docId": "plot.fanren-1429-1434-zhuyinzi-jiaojichang-shitan",
        "seq": 1429
      },
      {
        "value": "试炼目标",
        "docId": "plot.fanren-1438-yin-zhu-feng",
        "seq": 1435
      }
    ],
    "稀有度": [
      {
        "value": "约五百年成熟一次、每株一枚",
        "docId": "plot.fanren-1429-1434-zhuyinzi-jiaojichang-shitan",
        "seq": 1429
      },
      {
        "value": "罕见",
        "docId": "plot.fanren-1447-1452-blood-puppets-and-pet-advance",
        "seq": 1447
      }
    ],
    "产地": [
      {
        "value": "地渊（秽气最浓处，三层必有）",
        "docId": "plot.fanren-1429-1434-zhuyinzi-jiaojichang-shitan",
        "seq": 1429
      },
      {
        "value": "地渊深层",
        "docId": "plot.fanren-1438-yin-zhu-feng",
        "seq": 1435
      },
      {
        "value": "地渊二层",
        "docId": "plot.fanren-1438-yin-zhu-feng",
        "seq": 1435
      },
      {
        "value": "冰煞之地",
        "docId": "plot.fanren-ch1441-1446-bingsha-wanteng",
        "seq": 1441
      },
      {
        "value": "地渊腐叶林深处水潭边",
        "docId": "plot.fanren-1447-1452-blood-puppets-and-pet-advance",
        "seq": 1447
      },
      {
        "value": "地渊",
        "docId": "plot.fanren-1457-taodun-didi-escape",
        "seq": 1453
      }
    ]
  },
  "firstSeq": 1429,
  "attrProvenance": {
    "类型": {
      "asOf": null,
      "docId": "plot.fanren-1447-1452-blood-puppets-and-pet-advance",
      "dated": false,
      "seq": 1447
    },
    "用途": {
      "asOf": null,
      "docId": "plot.fanren-1438-yin-zhu-feng",
      "dated": false,
      "seq": 1435
    },
    "稀有度": {
      "asOf": null,
      "docId": "plot.fanren-1447-1452-blood-puppets-and-pet-advance",
      "dated": false,
      "seq": 1447
    },
    "产地": {
      "asOf": null,
      "docId": "plot.fanren-1429-1434-zhuyinzi-jiaojichang-shitan",
      "dated": false,
      "seq": 1429
    }
  },
  "contested": false,
  "contradictions": {},
  "docs": [
    "plot.fanren-1429-1434-zhuyinzi-jiaojichang-shitan",
    "plot.fanren-1438-yin-zhu-feng",
    "plot.fanren-ch1441-1446-bingsha-wanteng",
    "plot.fanren-1447-1452-blood-puppets-and-pet-advance",
    "plot.fanren-1457-taodun-didi-escape"
  ],
  "updatedAt": "2026-06-16T17:08:35.936Z"
}
