{
  "id": "ent.formation.x-df4abcac",
  "type": "formation",
  "name": "同命禁制",
  "aliases": [],
  "summary": "华西仙子对无垢老祖所下的同命禁制，意在同生共死，已被无垢老祖于数年前破解。",
  "attributes": {
    "效果": "同生共死",
    "破解法": "无垢老祖已于数年前破解",
    "布置者": "华西仙子"
  },
  "observations": {
    "效果": [
      {
        "value": "同生共死",
        "docId": "plot.fanren-2347-2352-zhan-wu-zu",
        "seq": 2347
      }
    ],
    "破解法": [
      {
        "value": "无垢老祖已于数年前破解",
        "docId": "plot.fanren-2347-2352-zhan-wu-zu",
        "seq": 2347
      }
    ],
    "布置者": [
      {
        "value": "华西仙子",
        "docId": "plot.fanren-2347-2352-zhan-wu-zu",
        "seq": 2347
      }
    ]
  },
  "firstSeq": 2347,
  "attrProvenance": {
    "效果": {
      "asOf": null,
      "docId": "plot.fanren-2347-2352-zhan-wu-zu",
      "dated": false,
      "seq": 2347
    },
    "破解法": {
      "asOf": null,
      "docId": "plot.fanren-2347-2352-zhan-wu-zu",
      "dated": false,
      "seq": 2347
    },
    "布置者": {
      "asOf": null,
      "docId": "plot.fanren-2347-2352-zhan-wu-zu",
      "dated": false,
      "seq": 2347
    }
  },
  "contested": false,
  "contradictions": {},
  "docs": [
    "plot.fanren-2347-2352-zhan-wu-zu"
  ],
  "updatedAt": "2026-06-21T18:28:45.146Z"
}
