{
  "id": "ent.formation.x-2ac95b96",
  "type": "formation",
  "name": "五行迷踪阵",
  "aliases": [
    "五行迷踪"
  ],
  "summary": "以五杆白色迷踪旗布下的幻阵,需五人各持一旗,黄雾化幻境困敌、令其原地打转,只困不伤。",
  "attributes": {
    "效果": "幻阵困敌、只困不伤、困缚妖兽、困住妖兽",
    "布置者": "隐剑峰弟子",
    "出处": "向内门师兄所借迷踪阵旗"
  },
  "observations": {
    "效果": [
      {
        "value": "幻阵困敌、只困不伤",
        "docId": "plot.fanren-ch560-guishu",
        "seq": 601
      },
      {
        "value": "困缚妖兽",
        "docId": "plot.fanren-607-612-xueyunhu-heiyishaofu-qingjinshi-shishi",
        "seq": 607
      },
      {
        "value": "困住妖兽",
        "docId": "plot.fanren-607-612-xueyunhu-heiyi-shaofu-lingyan-yu",
        "seq": 607
      }
    ],
    "布置者": [
      {
        "value": "奎焕、王师兄、韩立等五人",
        "docId": "plot.fanren-ch560-guishu",
        "seq": 601
      },
      {
        "value": "隐剑峰弟子",
        "docId": "plot.fanren-607-612-xueyunhu-heiyishaofu-qingjinshi-shishi",
        "seq": 607
      }
    ],
    "出处": [
      {
        "value": "向内门师兄所借迷踪阵旗",
        "docId": "plot.fanren-ch560-guishu",
        "seq": 601
      }
    ]
  },
  "firstSeq": 601,
  "attrProvenance": {
    "效果": {
      "asOf": null,
      "docId": "plot.fanren-ch560-guishu",
      "dated": false,
      "seq": 601
    },
    "布置者": {
      "asOf": null,
      "docId": "plot.fanren-607-612-xueyunhu-heiyishaofu-qingjinshi-shishi",
      "dated": false,
      "seq": 607
    },
    "出处": {
      "asOf": null,
      "docId": "plot.fanren-ch560-guishu",
      "dated": false,
      "seq": 601
    }
  },
  "contested": false,
  "contradictions": {},
  "docs": [
    "plot.fanren-ch560-guishu",
    "plot.fanren-607-612-xueyunhu-heiyishaofu-qingjinshi-shishi",
    "plot.fanren-607-612-xueyunhu-heiyi-shaofu-lingyan-yu"
  ],
  "updatedAt": "2026-06-17T07:58:36.449Z"
}
