{
  "id": "plot.fanren-ch103-108-jiayuancheng-subdue-sun-ergou-jingjiaohui-intel",
  "title": "凡人修仙传 第103-108章：收服孙二狗、惊蛟会情报与吴剑鸣抢身份",
  "kind": "plot",
  "summary": "韩立在嘉元城码头令曲魂屠灭来犯帮众、亲手刺杀铁拳会黑熊，以腐心丸收服地头蛇孙二狗为耳目；借其情报与墨大夫遗书摸清惊蛟会现状，惊悉墨居仁早被传死、其‘关门弟子’吴剑鸣已抢先冒充身份混入墨府并将与墨玉珠成婚。",
  "topics": [
    "凡人修仙传",
    "嘉元城",
    "惊蛟会",
    "韩立收服",
    "墨大夫遗书",
    "章节剧情",
    "墨府",
    "升仙会"
  ],
  "keywords": [
    "韩立",
    "曲魂",
    "铁奴",
    "孙二狗",
    "黑熊",
    "腐心丸",
    "嘉元城",
    "惊蛟会",
    "墨大夫",
    "墨居仁",
    "鬼手",
    "吴剑鸣",
    "墨玉珠",
    "严夫人",
    "暖阳宝玉",
    "四平帮",
    "铁拳会",
    "兄弟盟",
    "天霸门",
    "岚州",
    "阴寒之毒",
    "汇源客栈",
    "猿臂沈重山",
    "魔银手",
    "困龙功",
    "Han Li",
    "Jingjiaohui",
    "凡人修仙传",
    "第106章",
    "第107章",
    "第108章",
    "蓝衣人",
    "老四",
    "黄衫男子",
    "墨府三骄",
    "墨彩环",
    "严氏",
    "吴公子",
    "升仙会",
    "升仙大会",
    "暗舵",
    "五娘",
    "天眼术",
    "筑基丹",
    "南陵街",
    "香家酒楼",
    "夜入墨府",
    "汤二"
  ],
  "keyFacts": [
    "韩立在嘉元城西城码头以软剑一剑刺穿喉咙杀死铁拳会头目黑熊，曲魂(铁奴)击倒二十余名大汉。",
    "韩立给孙二狗服下独门秘药‘腐心丸’(一月须服一次解药，否则五脏糜烂而死)，将其收服为打探嘉元城情报的手下。",
    "孙二狗是嘉元城西城四平帮的码头管事；四平帮近千帮众，帮主为猿臂沈重山。",
    "墨大夫遗书显示其创立惊蛟会(曾为岚州三大霸主之一)，总舵设在嘉元城，本名墨居仁，号鬼手。",
    "嘉元城现三大帮会为兄弟盟、惊蛟会、天霸门，天霸门最强据东城、惊蛟会最弱据南城，四足鼎立。",
    "惊蛟会数年前突然衰败，现由墨居仁四夫人严氏(遗孀)主持。",
    "一年前一名自称墨居仁关门弟子的吴剑鸣携遗书信物到墨府报丧，并已与墨府千金墨玉珠定亲、即将成婚。",
    "韩立丹田阴寒之毒已凝成豌豆大黑团并扩散，估计两月内爆发，必须夺取墨府‘暖阳宝玉’解毒。",
    "韩立在嘉元城南陵街、墨府对面的香家酒楼二楼蹲守打探墨府消息。",
    "韩立首次遇到法力远胜自己的修仙者——蓝衣人，被对方一眼看穿般的眼神震慑，但蓝衣人未出手便离去。",
    "蓝衣人（老四）刚练成基础功法第十层（服用筑基丹所致），与黄衫男子（二哥）等同伴一同来岚州参加每十年一次的升仙会。",
    "蓝衣人目测韩立法力仅基础功法七八层、十七八岁，断定其只是跟长辈来长见识。",
    "墨府三骄指墨大夫两位亲生女儿与一位义女；大小姐墨玉珠为嘉元城第一美女，定亲对象为吴公子吴剑鸣。",
    "吴剑鸣是墨大夫对头派来的冒牌货/试探者，曾连败十六名情敌、与墨玉珠看似情深，实为伪婚拖延。",
    "韩立的目标是夺取墨府的暖阳宝玉，以克制体内随时可能提前爆发的阴毒。",
    "韩立午夜化为轻烟潜入墨府后院，发现有人种植草药（疑似继承墨大夫医术）。",
    "韩立偷听到严氏（墨大夫之妻、惊蛟会代理当家人）与女儿墨彩环密谈：惊蛟会衰弱，最大支柱暗舵由五娘独掌，月送银两递减，且早年马叔等人闹分立。",
    "严氏母女证实已查明吴剑鸣是假货，但因敌方声势太大，只能牺牲墨玉珠名誉、与其虚与委蛇拖延时间。"
  ],
  "entities": [
    "ent.person.x-b7ad490e",
    "ent.person.x-2d3ced49",
    "ent.person.x-788415f2",
    "ent.person.x-7e36a524",
    "ent.person.x-5470ae64",
    "ent.person.x-91f3af5a",
    "ent.person.x-32a20475",
    "ent.person.x-18589ca5",
    "ent.person.x-b6a046ab",
    "ent.person.x-8b661ce4",
    "ent.person.x-fa158443",
    "ent.person.x-8c62723f",
    "ent.faction.x-5a7e04c9",
    "ent.place.x-6d1f1283",
    "ent.place.x-642c7d96",
    "ent.place.x-af675f29",
    "ent.place.x-0c11c800",
    "ent.place.x-69c271c2",
    "ent.event.x-49111d19",
    "ent.item.x-3e241ed9",
    "ent.spell.x-1fc84abc",
    "ent.pill.x-bbccd856"
  ],
  "fromSeq": 103,
  "toSeq": 108,
  "asOf": "2026-06-14",
  "timeSensitive": false,
  "validUntil": null
}
